ipypm/__init__.py
ipypm/_version.py
ipypm/analyze_tab.py
ipypm/compare_tab.py
ipypm/edit_connectors_tab.py
ipypm/edit_tab.py
ipypm/explore_tab.py
ipypm/ipypm.py
ipypm/main_tab.py
ipypm/mcmc_tab.py
ipypm/open_tab.py
ipypm/settings_tab.py
ipypm/tests/__init__.py
ipypm/tests/test_ipypm.py
ipypm-0.2.16.dist-info/AUTHORS.rst
ipypm-0.2.16.dist-info/LICENSE
ipypm-0.2.16.dist-info/METADATA
ipypm-0.2.16.dist-info/WHEEL
ipypm-0.2.16.dist-info/top_level.txt
ipypm-0.2.16.dist-info/RECORD
