Metadata-Version: 2.1
Name: ipypm
Version: 0.2.16
Summary: GUI for pyPM.ca Population Modeler
Home-page: http://www.pypm.ca
Author: Dean Karlen
Author-email: karlen@uvic.ca
License: GNU General Public License v3
Keywords: ipypm
Platform: UNKNOWN
Classifier: Development Status :: 4 - Beta
Classifier: Intended Audience :: End Users/Desktop
Classifier: License :: OSI Approved :: GNU General Public License v3 (GPLv3)
Classifier: Natural Language :: English
Classifier: Programming Language :: Python :: 3
Classifier: Programming Language :: Python :: 3.5
Classifier: Programming Language :: Python :: 3.6
Classifier: Programming Language :: Python :: 3.7
Classifier: Programming Language :: Python :: 3.8
Requires-Python: >=3.5
Requires-Dist: pypmca
Requires-Dist: scipy
Requires-Dist: numpy
Requires-Dist: ipywidgets
Requires-Dist: texttable
Requires-Dist: matplotlib
Requires-Dist: requests
Requires-Dist: pandas
